{
    "homepage": "https://github.com/VSCodium/vscodium",
    "version": "1.69.1",
    "license": "MIT",
    "description": "Binary releases of VS Code without MS branding/telemetry/licensing (Portable Edition w/o context menu installer). China TUNA mirror.",
    "architecture": {
        "64bit": {
            "url": "https://mirrors.tuna.tsinghua.edu.cn/github-release/VSCodium/vscodium/1.69.1/VSCodium-win32-x64-1.69.1.zip",
            "hash": "6560db9d6e353c248354fb2d3a7cd87407a519bf0b1b763d8110095c3df9095b"
        },
        "32bit": {
            "url": "https://mirrors.tuna.tsinghua.edu.cn/github-release/VSCodium/vscodium/1.69.1/VSCodium-win32-ia32-1.69.1.zip",
            "hash": "93273cc0b2c00aeb0b28bcb07ec6cc5d6855cfd9553bfd18147160a8c50b52b5"
        }
    },
    "bin": [
        [
            "bin\\codium.cmd",
            "codium"
        ]
    ],
    "shortcuts": [
        [
            "VSCodium.exe",
            "VSCodium"
        ]
    ],
    "persist": "data",
    "checkver": "github",
    "autoupdate": {
        "architecture": {
            "64bit": {
                "url": "https://mirrors.tuna.tsinghua.edu.cn/github-release/VSCodium/vscodium/$version/VSCodium-win32-x64-$version.zip"
            },
            "32bit": {
                "url": "https://mirrors.tuna.tsinghua.edu.cn/github-release/VSCodium/vscodium/$version/VSCodium-win32-ia32-$version.zip"
            }
        },
        "hash": {
            "url": "$url.sha256"
        }
    }
}
