{
    "homepage": "https://mirrors.tuna.tsinghua.edu.cn/github-release/VSCodium/vscodium",
    "version": "1.51.0",
    "license": "MIT",
    "description": "Binary releases of VS Code without MS branding/telemetry/licensing (Portable Edition w/o context menu installer). TUNA mirror.",
    "architecture": {
        "64bit": {
            "url": "https://mirrors.tuna.tsinghua.edu.cn/github-release/VSCodium/vscodium/1.51.0/VSCodium-win32-x64-1.51.0.zip",
            "hash": "78f8e65c94cc909bb593abbfa2d5b67c309b8d601c134dc53c0fd59ee2b2c84b"
        },
        "32bit": {
            "url": "https://mirrors.tuna.tsinghua.edu.cn/github-release/VSCodium/vscodium/1.51.0/VSCodium-win32-ia32-1.51.0.zip",
            "hash": "165f92ed29c1551efa99f80b68e9afaad888a70fb6a4579624749439b8eb0997"
        }
    },
    "bin": [
        [
            "bin\\codium.cmd",
            "codium"
        ]
    ],
    "shortcuts": [
        [
            "VSCodium.exe",
            "VSCodium"
        ]
    ],
    "persist": "data",
    "checkver": {
        "url": "https://github.com/VSCodium/vscodium",
        "regex": "/releases/tag/(?:v|V)?([\\d.]+)"
    },
    "autoupdate": {
        "architecture": {
            "64bit": {
                "url": "https://mirrors.tuna.tsinghua.edu.cn/github-release/VSCodium/vscodium/$version/VSCodium-win32-x64-$version.zip"
            },
            "32bit": {
                "url": "https://mirrors.tuna.tsinghua.edu.cn/github-release/VSCodium/vscodium/$version/VSCodium-win32-ia32-$version.zip"
            }
        },
        "hash": {
            "url": "$url.sha256"
        }
    }
}
