{
    "homepage": "https://github.com/VSCodium/vscodium",
    "version": "1.66.2",
    "license": "MIT",
    "description": "Binary releases of VS Code without MS branding/telemetry/licensing (Portable Edition w/o context menu installer). China BFSU mirror.",
    "architecture": {
        "64bit": {
            "url": "https://mirrors.bfsu.edu.cn/github-release/VSCodium/vscodium/1.66.2/VSCodium-win32-x64-1.66.2.zip",
            "hash": "b797fccb71cf4d176ecb458a812b50a6add9d1f4bb3ff124defa9d6a2a318db0"
        },
        "32bit": {
            "url": "https://mirrors.bfsu.edu.cn/github-release/VSCodium/vscodium/1.66.2/VSCodium-win32-ia32-1.66.2.zip",
            "hash": "2c7b832652973b4117168854aa15e30ed6516333b1ebbfa4a548a0a3303f53c6"
        }
    },
    "bin": [
        [
            "bin\\codium.cmd",
            "codium"
        ]
    ],
    "shortcuts": [
        [
            "VSCodium.exe",
            "VSCodium"
        ]
    ],
    "persist": "data",
    "checkver": "github",
    "autoupdate": {
        "architecture": {
            "64bit": {
                "url": "https://mirrors.bfsu.edu.cn/github-release/VSCodium/vscodium/$version/VSCodium-win32-x64-$version.zip"
            },
            "32bit": {
                "url": "https://mirrors.bfsu.edu.cn/github-release/VSCodium/vscodium/$version/VSCodium-win32-ia32-$version.zip"
            }
        },
        "hash": {
            "url": "$url.sha256"
        }
    }
}
